pytest_splinter4/__init__.py
pytest_splinter4/executable_path.py
pytest_splinter4/options.py
pytest_splinter4/plugin.py
pytest_splinter4/webdriver_patches.py
pytest_splinter4/xdist_plugin.py
pytest_splinter4/profiles/firefox/.marker
pytest_splinter4-0.4.0.dist-info/AUTHORS.rst
pytest_splinter4-0.4.0.dist-info/LICENSE.txt
pytest_splinter4-0.4.0.dist-info/METADATA
pytest_splinter4-0.4.0.dist-info/WHEEL
pytest_splinter4-0.4.0.dist-info/entry_points.txt
pytest_splinter4-0.4.0.dist-info/top_level.txt
pytest_splinter4-0.4.0.dist-info/RECORD
