Metadata-Version: 2.1
Name: pytest-splinter4
Version: 0.4.0
Summary: Pytest plugin for the splinter automation library
Home-page: https://github.com/jsfehler/pytest-splinter4
Author: Joshua Fehler
License: MIT license
Classifier: Development Status :: 6 - Mature
Classifier: Intended Audience :: Developers
Classifier: License :: OSI Approved :: MIT License
Classifier: Operating System :: POSIX
Classifier: Operating System :: Microsoft :: Windows
Classifier: Operating System :: MacOS :: MacOS X
Classifier: Topic :: Software Development :: Testing
Classifier: Topic :: Software Development :: Libraries
Classifier: Topic :: Utilities
Classifier: Programming Language :: Python :: 3
Classifier: Programming Language :: Python :: 3.8
Classifier: Programming Language :: Python :: 3.9
Classifier: Programming Language :: Python :: 3.10
Classifier: Programming Language :: Python :: 3.11
Classifier: Programming Language :: Python :: 3.12
License-File: LICENSE.txt
License-File: AUTHORS.rst
Requires-Dist: splinter >=0.21.0
Requires-Dist: pytest >=8.0.0
